Metadata-Version: 2.1
Name: prospective
Version: 0.1.1
Summary: Categorical data generator
Home-page: https://github.com/timkpaine/prospective
Author: Tim Paine
Author-email: t.paine154@gmail.com
License: Apache 2.0
Keywords: finance data
Platform: UNKNOWN
Classifier: Development Status :: 4 - Beta
Classifier: Programming Language :: Python :: 3
Classifier: Programming Language :: Python :: 3.7
Classifier: Programming Language :: Python :: 3.8
Classifier: Programming Language :: Python :: 3.9
Classifier: Programming Language :: Python :: 3.10
Provides-Extra: dev
License-File: LICENSE
License-File: AUTHORS
